tcranno/FindClosestSeq.py
tcranno/__init__.py
tcranno/core_analysis.py
tcranno/model_predict.py
tcranno/plot_landscape.py
tcranno/population_analysis.py
tcranno/repertoire_analysis.py
tcranno/run_tcr2eao.py
tcranno/run_tcr2tcr.py
tcranno/data/DB_FULL.pkl
tcranno/data/DB_FULL_AG_ORG_key_map.pkl
tcranno/data/DB_FULL_VDJ.pkl
tcranno/data/IEDB.pkl
tcranno/data/IEDB_VDJ.pkl
tcranno/data/VJ_map.pkl
tcranno/example/example.py
tcranno/example/example.sh
tcranno/example/example_input_repertoire.tsv
tcranno/pretrained/pretrained_encoder.h5
tcranno-1.0.2.dist-info/LICENSE
tcranno-1.0.2.dist-info/METADATA
tcranno-1.0.2.dist-info/WHEEL
tcranno-1.0.2.dist-info/top_level.txt
tcranno-1.0.2.dist-info/zip-safe
tcranno-1.0.2.dist-info/RECORD
