Metadata-Version: 2.1
Name: tcranno
Version: 1.0.2
Summary: TCR repertoire specificity annotation toolkit
Home-page: https://github.com/deepomicslab/TCRanno
Author: LUO Jiaqi
Classifier: Programming Language :: Python :: 3
Classifier: License :: OSI Approved :: MIT License
Classifier: Operating System :: OS Independent
License-File: LICENSE
